intan/__init__.py
intan/control/__init__.py
intan/control/_messaging.py
intan/io/__init__.py
intan/io/_block_parser.py
intan/io/_channel_utils.py
intan/io/_data_processing.py
intan/io/_exceptions.py
intan/io/_file_utils.py
intan/io/_header_parsing.py
intan/io/_metadata_utils.py
intan/io/_rhd_loader.py
intan/plotting/__init__.py
intan/plotting/_emg_plots.py
intan/plotting/_waterfall.py
intan/processing/__init__.py
intan/processing/_filters.py
intan/processing/_metrics_utils.py
python_intan-0.0.2.dist-info/licenses/LICENSE
python_intan-0.0.2.dist-info/METADATA
python_intan-0.0.2.dist-info/WHEEL
python_intan-0.0.2.dist-info/top_level.txt
python_intan-0.0.2.dist-info/RECORD
