Metadata-Version: 2.4
Name: python-intan
Version: 0.0.2
Summary: Python utilities for working with Intan electrophysiology data
Author-email: Jonathan Shulgach <jshulgac@andrew.cmu.edu>
License-Expression: MIT
Project-URL: Homepage, https://github.com/Neuro-Mechatronics-Interfaces/python-intan
Keywords: intan,emg,neurotech,signal processing,biomedical
Requires-Python: >=3.10
License-File: LICENSE
Requires-Dist: numpy>=1.26.0
Requires-Dist: scipy==1.14.1
Requires-Dist: matplotlib
Requires-Dist: pandas
Requires-Dist: PySerial
Requires-Dist: scikit-learn
Dynamic: license-file
